BriqPythonSdk/__init__.py
BriqPythonSdk/client.py
BriqPythonSdk-0.1.0.dist-info/LICENSE
BriqPythonSdk-0.1.0.dist-info/METADATA
BriqPythonSdk-0.1.0.dist-info/WHEEL
BriqPythonSdk-0.1.0.dist-info/top_level.txt
BriqPythonSdk-0.1.0.dist-info/RECORD
