Metadata-Version: 2.1
Name: BriqPythonSdk
Version: 0.1.0
Summary: Python SDK for the Briq messaging API
Home-page: https://github.com/snavid/BriqPythonSdk
Author: snavid
Author-email: snavidux.official@gmail.com
Classifier: Programming Language :: Python :: 3
Classifier: Programming Language :: Python :: 3.7
Classifier: Programming Language :: Python :: 3.8
Classifier: Programming Language :: Python :: 3.9
Classifier: Programming Language :: Python :: 3.10
Classifier: License :: OSI Approved :: MIT License
Classifier: Operating System :: OS Independent
Requires-Python: >=3.7
License-File: LICENSE
Requires-Dist: requests >=2.25.0
